.gitignore
.stickler.yml
.travis.yml
setup.py
tox.ini
.github/main.workflow
aimdfragmentation/__init__.py
aimdfragmentation/c_stack.cpp
aimdfragmentation/c_stack.h
aimdfragmentation/dps.pyx
aimdfragmentation/frag.py
aimdfragmentation.egg-info/PKG-INFO
aimdfragmentation.egg-info/SOURCES.txt
aimdfragmentation.egg-info/dependency_links.txt
aimdfragmentation.egg-info/requires.txt
aimdfragmentation.egg-info/top_level.txt
aimdfragmentation.egg-info/zip-safe
aimdfragmentation/test/__init__.py
aimdfragmentation/test/test.xyz
aimdfragmentation/test/test_fragment.py
docs/README.md
examples/ch4.xyz
examples/energy.dat
examples/example.py
examples/force.dat