Metadata-Version: 2.1
Name: aimdfragmentation
Version: 1.0.29
Summary: AIMD Fragmentation Calculation
Home-page: https://github.com/njzjz/aimdfragmentation
Author: Jinzhe Zeng
Author-email: jzzeng@stu.ecnu.edu.cn
License: UNKNOWN
Keywords: AIMD Fragmentation
Platform: UNKNOWN
Classifier: Natural Language :: English
Classifier: Operating System :: POSIX :: Linux
Classifier: Operating System :: Microsoft :: Windows
Classifier: Programming Language :: Python :: 3.6
Classifier: Programming Language :: Python :: 3.7
Classifier: Topic :: Scientific/Engineering :: Chemistry
Classifier: Topic :: Software Development :: Libraries :: Python Modules
Classifier: Topic :: Software Development :: Version Control :: Git
Requires-Python: ~=3.6
Provides-Extra: test
